charabia.py
charabia-2.0.0.dist-info/LICENSE
charabia-2.0.0.dist-info/METADATA
charabia-2.0.0.dist-info/WHEEL
charabia-2.0.0.dist-info/top_level.txt
charabia-2.0.0.dist-info/RECORD
