Metadata-Version: 2.1
Name: charabia
Version: 2.0.0
Summary: Library designed for reversible sheltering of sensitive information/data, meaning you can shelter strings or tokens using this encoder.
Home-page: https://github.com/Kreusada/Charabia
Author: Kreusada
Author-email: kreusadaprojects@gmail.com
License: UNKNOWN
Platform: UNKNOWN
Classifier: License :: OSI Approved :: MIT License
Classifier: Operating System :: OS Independent
Classifier: Natural Language :: English
Classifier: Programming Language :: Python :: 3.6
Classifier: Programming Language :: Python :: 3.7
Classifier: Programming Language :: Python :: 3.8
Classifier: Programming Language :: Python :: 3.9
Classifier: Programming Language :: Python :: 3.10
License-File: LICENSE
